{"total": 333, "count_0day": 115, "count_1day": 125, "count_nday": 93, "files": ["万户_万户oa-name_judge-jsp-sql注入.toml", "浪潮_浪潮云财务系统-cwba-se-service-gsp_unitdefinewebservice-asmx-命令执行.toml", "用友_用友-u8-crm客户关系管理系统-checkselectpartapply-php-接口存在sql注入.toml", "用友_用友nc-baplink-sql注入.toml", "畅捷通_畅捷通t-tplus-ajaxpro-ufida-t-aa-fi-uip-accountassociationeditlistcontroller-ufida-t-aa-fi-uip-ashx-命令执.toml", "索贝_索贝内容管理系统-search-full-search-信息泄露.toml", "索贝_索贝内容管理系统-sobey-mcheditor-mch-articlelist-getlist-sql注入.toml", "金和_金和-c6-checkpwd-aspx-存在xxe漏洞.toml", "astrbot_astrbot路径遍历.toml", "xwiki_xwiki-getdeleteddocuments-vm-sql注入.toml", "东胜物流_东胜物流软件-dswebservice-asmx-sql注入.toml", "天锐_天锐绿盾审批系统-sysadmin-信息泄露.toml", "契约锁_契约锁电子签章系统存在远程代码执行.toml", "时空智友_时空智友企业流程化管控系统xml外部实体注入.toml", "朗新天霁_朗新天霁ehr-sql注入.toml", "汉王_汉王e脸通综合管理平台-querydoorinfolist-do-sql注入.toml", "科立讯_科立讯指挥调度管理平台存在sql注入.toml", "红帆_红帆oa-netcauserlogin-aspx存在sql注入.toml", "孚盟云_孚盟云getimage-aspx-sql注入.toml", "安数云_安数云综合日志分析系统远程代码执行.toml", "汉王_汉王e脸通综合管理平台-uploadblacklistfile-do-任意文件上传.toml", "金和_金和oa-dailytasklistinfo-aspx-sql注入.toml", "南昊_南昊网上阅卷系统biaozhi_paper-jsp-sql注入.toml", "网仕_上海网仕科技-transcoder-ms-index-php-sql注入.toml", "联软_联软unisdp-零信任访问控制系统-emm-core-oauth-token-信息泄露.toml", "letta_letta平台-ai代理框架-远程代码执行cve-2025-51482.toml", "万户_万户oa存在sql注入.toml", "东胜物流_东胜物流软件-workflowgridsource-aspx-sql注入.toml", "天翼视联_天翼视联指挥调度管理平台uploadgps-php存在sql注入.toml", "帆软_帆软报表dbcommit代码执行.toml", "海信_海信智能公交企业管理系统sql注入.toml", "深大_深大智能科技管控平台服务端api-asmx-sql注入.toml", "灵当_灵当crm-copylinktocontent-ssrf漏洞.toml", "用友_用友nmc服务任意文件上传.toml", "用友_用友u8-cloud-querysoapservlet-存在sql注入.toml", "科讯_科讯新职教网校系统checkpaystatus存在sql注入.toml", "维达_维达外贸客户关系管理系统-sendmailview-jsp-sql注入.toml", "致远_致远a8-component-do-存在认证绕过导致远程代码执行.toml", "金和_金和oa-archivesfiletracesearch存在sql注入.toml", "journalx_journalx-期刊稿件采编系统-resume-任意文件读取.toml", "journalx_journalx-期刊稿件采编系统-reviewerregister-任意文件读取.toml", "东胜物流_东胜物流软件fileexport-aspx-任意文件读取.toml", "中科汇联_中科汇联-easysite-系统xstream-反序列化.toml", "微软_microsoft-sharepoint-server远程代码执行漏洞-cve-2025-53770.toml", "明源_明源地产-erp-datarulexmlhttp-aspx-sql-注入.toml", "汉王_汉王e脸通综合管理平台getfirstemp-do-sql注入.toml", "汉王_汉王e脸通综合管理平台querymeetingroom-do-sql注入.toml", "科汛_科汛新职教网校系统checkpaystatus-sql-注入.toml", "迪博_迪博行政管理系统-export_handle-jsp任意文件读取漏洞.toml", "jeecg-boot_jeecg-boot-sql注入.toml", "久其_久其财务报表系统存在命令执行.toml", "奇安信_奇安信secfox运维安全管理与审计系统存在命令执行cnvd-2025-16451.toml", "汉王_汉王efacego-monadfileupload-do-任意文件上传.toml", "汉王_汉王e脸通综合管理平台exportresourcebyfilepath-do任意文件读取.toml", "汉王_汉王e脸通综合管理平台uploadmeetingfile-do任意文件上传.toml", "journalx_journalx-期刊稿件采编系统-resume-任意文件上传.toml", "东胜物流_东胜物流软件-wmszxfeegridsource-aspx-sql注入.toml", "东胜物流_东胜物流软件workflowgridsource-aspx-sql注入.toml", "九麒_杭州九麒科技-bigant-admin-任意文件读取.toml", "南昊_南昊网上阅卷系统paperjsp-sql-注入.toml", "大华_大华-dss-综合管理平台cascademodifylinkeddev-反序列化远程代码执行.toml", "大蚂蚁_大蚂蚁即时通讯down-html-任意文件读取.toml", "天运通_天运通-pactl-upload-任意文件上传.toml", "宏景_宏景人力资源管理系统orgsettree-sql-注入漏洞.toml", "汉王_汉王efacego-updatevisitormapconfig-do任意文件上传.toml", "海信_海信智能公交企业管理系统busdefassgnmanagement-aspx-sql-注入.toml", "满客宝_满客宝后台管理系统downloadproviderfile-任意文件读取.toml", "用友_用友-u9-cloud-pdfdirectprint-aspx-反序列化.toml", "用友_用友oa系统u8cloud-filtercondaction-sql注入.toml", "百易云_百易云资产管理运营系统-sql-注入.toml", "群杰_群杰印章密码重置.toml", "胜意_胜意费控云-connect-接口ssrf.toml", "蓝凌_蓝凌-eis-智慧协同平台dingusers-aspx-sql-注入.toml", "金和_金和-c6-deltemp-aspxxml-实体注入致任意文件读取漏洞cve-2025-7523.toml", "金蝶_金蝶企业移动管理云uploadpackageaction-文件上传.toml", "驰骋_驰骋-bpm-低代码开发平台richuploadfile-任意文件上传.toml", "jielink_jielink-智能终端操作平台-deletelppool-sql-注入.toml", "laravel_laravel-larecipe-renderblade未授权代码注入.toml", "sawtooth_sawtoothsoftware-lighthouse-studio远程代码执行.toml", "孚盟云_孚盟云-getimage-aspx-sql注入.toml", "孚盟云_孚盟云-getpic-sql注入.toml", "安恒_安恒ailpha任意用户登录.toml", "安数云_安数云综合日志分析系统远程命令执行.toml", "方向标_方向标邮件网关存在rce漏洞.toml", "朗新天霁_朗新天霁-ehr-gettrans-asmx-sql-注入.toml", "汉王_汉王e脸通export-resourcebyfilepath-do存在任意文件读取.toml", "深信服_深信服服务端rce.toml", "深信服_深信服零信任linux版本提权cve-2025-52923.toml", "绿盟_亿赛通电子文档安全管理系统usersservice序列化漏洞.toml", "美特_美特crm-download-new-任意文件读取.toml", "腾讯_微信3-9-1click-rce.toml", "金蝶_金蝶云星空-devreportservice-getbusinessobjectdata-common-kdsvc-远程代码执行.toml", "金蝶_金蝶云星空-inoutdataservice-getmportoutdata-common-kdsvc-远程代码执行.toml", "锐捷_锐捷-eweb-路由器-ipam-php-任意文件读取.toml", "grafana_grafana跨站脚本cve-2025-4123.toml", "oracle_oracle多个漏洞-分不清了.toml", "微软_windows-远程代码执行漏洞-cve-2025-47981.toml", "泛微_泛微e-cology9-前台sql注入.toml", "深信服_深信服vpn任意用户添加.toml", "深信服_深信服vpn用户密码未授权修改.toml", "金山_wps未授权访问导致rce.toml", "oracle_oracle-weblogic-server-未授权访问-cve-2025-30762.toml", "zimbra_zimbracollaboration-suite-安全漏洞-cve-2025-53645.toml", "用友_用友yonbip-r6旗舰版-任意用户密码重置.toml", "金和_金和oa-moduletaskview-aspx-sql注入.toml", "金蝶_金蝶云星空-dynamicformservice-closeform-common-kdsvc-远程代码执行.toml", "geoserver_geoserver-rest-api-存在未授权访问漏洞-cve-2025-27505.toml", "亿邮_亿邮电子邮件系统认证逻辑缺陷.toml", "亿邮_亿邮邮件网关-rce.toml", "大华_大华icc-evo-runs-v1-0-push-rce.toml", "微软_microsoft-excel-2024远程代码执行漏洞-cve-2025-47165.toml", "汉王_汉王e脸通综合管理平台-queryantisubmarinelist-do-存在sql注入.toml", "金和_金和oa-ishaveftask-aspx-存在sql注入.toml", "金和_金和oa-ishaveftask-aspx-存在xxe.toml", "飞塔_飞塔authorization-sql注入cve-2025-25257.toml", "中识_中识云平台-sys_user_list-接口存在信息泄露.toml", "数字通_数字通-mobile-document-update-parase-存在sql注入.toml", "昂捷_昂捷crm系统cwsuploadpicture任意文件读取.toml", "浪潮_浪潮gs的restfulserviceforweb-asmx存在sql注入.toml", "浪潮_浪潮财务管理系统-gspauditwebservice-asmx-存在反序列化.toml", "用友_用友-nc-imetawebservice4bqcloud-数据源-sql-注入.toml", "用友_用友-u9-cloud-远程代码执行.toml", "腾讯_微信发送a链接href可控.toml", "金蝶_金蝶云星空-businessdataservice-batchload-common-kdsvc-远程代码执行.toml", "龙采_龙采商城系统-auditing-接口存在sql注入.toml", "东胜物流_东胜物流软件wmszxfeegridsource-aspx-sql-注入漏洞.toml", "东胜物流_东胜物流软件workflowgridsource-aspx-sql-注入漏洞.toml", "南昊_南昊网上阅卷系统monitor-未授权访问漏洞.toml", "孚盟云_孚盟云-geticon-aspx-sql-注入.toml", "普华_普华powerpms-getfilesdata-sql注入.toml", "汉王_汉王-e-脸通综合管理平台updatevisitormapconfig-do-任意文件上传.toml", "美特_美特-crm-download-new-jsp-任意文件读取.toml", "jeecgboot_jeecgboot-gettotaldata任意用户密码重置.toml", "mailenable_mailenable-存在反射-xss-cve-2025-44148.toml", "mobileoa_智能办公系统-mobileoa-asmx-sql注入.toml", "东胜物流_东胜物流-softmng-fileinputhandler-upload-任意文件上传.toml", "大华_大华icc-evo-runs-v1-0-receive-rce.toml", "孚盟云_孚盟云crm-licmould-ashx-sql注入.toml", "汉王_汉王e脸通综合管理平台-imgdownload-do-任意文件读取.toml", "泛微_泛微e-cology-9存在sql注入.toml", "科立讯_福建科立讯通信有限公司-logout-php-sql注入.toml", "金和_金和oa-taskreportconfirm-aspx-sql注入.toml", "新炬_新炬网络智能运维管理平台agent-未授权远程命令执行漏洞.toml", "森鑫炬_森鑫炬税务企业综合运营平台file-get任意文件读取.toml", "汉王_汉王getvalidempforgroup-do-sql注入.toml", "灵当_灵当crm-xlsfileupload-php任意文件上传.toml", "美特_美特crm-mobileupload-jsp任意文件上传.toml", "金和_金和oa-addtask-sql注入.toml", "金和_金和oa-addtask-xxe.toml", "金和_金和oa-taskreportconfirm-apsx-sql注入.toml", "maildata_maildata邮件网关-0day.toml", "u-mail_u-mail-任意文件上传.toml", "webone_webone劳动力与考勤管理软件的-webforms-download-downloadfile-aspx接口存在任意文件读取.toml", "信呼_信呼oa-uploawaction-php-接口存在sql注入.toml", "博采_博采-cms-文件上传.toml", "大华_大华技术股份有限公司-dss-前台-ssrf.toml", "大华_大华智能物联综合管理平台.toml", "普华_普华科技-powerpms-forgotpassword-sql-注入.toml", "润乾_润乾报表任意文件写入漏洞.toml", "深信服_深信服vpn-远程代码执行.toml", "深信服_深信服零信任任意密码重置.toml", "用友_用友nc-getformitem-dopost-sql注入.toml", "用友_用友nc-getformltem-dopost-sql注入.toml", "用友_用友nccloud系统反序列化漏洞.toml", "用友_用友u9-cloud-print-dynamaticexport-aspx-接口任意文件下载.toml", "grafana_grafana-跨站点脚本-xss-cve-2025-4123.toml", "redis_redis-hyperloglog-远程代码执行-cve-2025-32023.toml", "richmail_richmail邮件openapiservice任意文件上传.toml", "wazuh_wazuh服务器远程代码执行漏洞-cve-2025-24016.toml", "zktime_zktime考勤管理系统iclock存在sql注入.toml", "宏景_宏景ehr-displayolecontent-任意文件读取.toml", "时空智友_时空智友erp系统-updater-uploadstudiofile-文件上传.toml", "汉王_汉王efacego-upload-do-任意文件上传.toml", "汉王_汉王e脸通-addvisitdeviceappointmentinfotest-do-fastjson反序列化rce.toml", "浪潮_浪潮gsp企业管理软件-payordersrv-asmx远程代码执行.toml", "用友_用友nc-deleteevent-sql注入.toml", "金和_金和oa-c6系统actiondataset接口xxe.toml", "citrix_citrix信息泄露cve-2023-4966.toml", "pws_pws-dashboard-存在任意文件读取漏洞-cve-2025-47423.toml", "redhat_centos-web-panel远程代码执行-cve-2025-48703.toml", "东胜物流_东胜物流-getbanklist-sql注入.toml", "东胜物流_东胜物流-getdatalist_salary-sql注入.toml", "华锐捷_华锐捷-监控综合管理平台uploadoffinemap任意文件上传.toml", "唯徳_唯徳知识产权管理系统任意文件读取.toml", "扁鹊医疗_扁鹊医疗getmonitorlist-sql注入.toml", "泛微_泛微datasource-update-jdbc远程代码执行.toml", "浪潮_浪潮gsp企业管理软件-srbbdefineservice-asmx-远程代码执行.toml", "用友_用友时空ksoa-sql注入.toml", "用友_用友畅捷通tplus-accountclearcontroler-sql注入.toml", "百易云_百易云资管系统imaread-make-php-sql注入.toml", "美特_美特crmdruid未授权访问.toml", "金蝶_金蝶eas-amf-endpoint反序列化.toml", "bossmail_bossmail-webmail-php-sql-注入漏洞.toml", "unibox_unibox路由器-pms_check-php-存在远程命令执行.toml", "亿邮_亿邮电子邮件系统远程命令执行漏洞.toml", "华天动力_华天软件-前台文件上传.toml", "南北软件_南北软件-erp-listdir-jsp-目录遍历漏洞.toml", "安科瑞_安科瑞智能环保云平台sql注入.toml", "时空智友_北京时空智友erp系统文件上传漏洞.toml", "汉王_汉王-e-脸通综合管理平台loginon-do任意文件读取漏洞.toml", "用友_用友-畅捷通t-glsyncservice-asmx-sql注入.toml", "用友_用友bip数据应用服务未授权访问.toml", "用友_用友fe协同平台存在文件上传.toml", "用友_用友nc-cloud-ibapioservice存在sql注入.toml", "用友_用友nc-listusersharingevents-sql注入漏洞.toml", "用友_用友nc-qrysubpurchaseorgbyparentpk-存在sql注入.toml", "用友_用友u8-cloud-filemanageservlet存在任意文件读取.toml", "畅捷通_用友-畅捷通t-getdecallusers-存在信息泄露.toml", "索贝_scms-索贝内容管理系统任意文件上传漏洞.toml", "绿盟_绿盟nips-users-json敏感信息泄漏.toml", "美特_美特-crm-headimgsave-sql-注入漏洞.toml", "群晖_群晖abm全局客户端密钥信息泄露cve-2025-4679.toml", "通达_通达oa-v2014-get_contactlist-php-敏感信息泄漏.toml", "通达_通达oa存在敏感信息泄露.toml", "jeecgboot_jeecgboot-框架passwordchange接口存在任意用户密码重置.toml", "unibox_unibox路由器update_byod-php-sql注入.toml", "九思_九思oa-未授权xxe漏洞.toml", "华天动力_华天软件inforcenter-plm前台文件上传.toml", "汉王_汉王e脸通getgroupemployee-do-sql注入.toml", "汉王_汉王queryalarmevent-do-sql注入.toml", "汉王_汉王querymanypeoplegrouplist-do-sql注入.toml", "泛微_泛微-eoffice-block_content-php-sql注入.toml", "泛微_泛微jdbc反序列化.toml", "泛微_泛微remarkoperate远程命令执行.toml", "浪潮_浪潮gs-purbidsupplementsrv-asmx任意文件读取.toml", "深信服_深信服堡垒机-netconfig-set_port-远程命令执行.toml", "理正_理正企业综合管理系统lzmis任意sql语句执行.toml", "紫光_紫光system-workflow-download任意文件读取.toml", "联想_联想网盘filez-filez-user-getusersession任意用户登录.toml", "金蝶_金蝶-apusic-应用中间件远程代码执行漏洞.toml", "金蝶_金蝶apusic应用服务器loadtree-jndi注入漏洞.toml", "akamai_akamai-cloudtest-soap-xxe漏洞-cve-2025-49493.toml", "easysite_easysite-内容管理平台反序列化漏洞.toml", "unibox_unibox路由器任意文件读取.toml", "webone_webone-劳动力与考勤管理套件-downloadfile-aspx-任意文件读取.toml", "东胜物流_东胜物流-commmng-print-uploadmailfile-任意文件上传.toml", "中科汇联_中科汇联easysite系统xstream反序列化.toml", "华易_华易企业管理云平台-home-zy-sql-注入.toml", "圣博润_圣博润堡垒机远程代码执行.toml", "天地伟业_天地伟业easy7downloadresource任意文件读取.toml", "帆软_帆软报表fr_remote_design文件上传.toml", "微软_smb提权cve-2025-33073.toml", "扁鹊医疗_扁鹊医疗getlyfsbyparams-sql注入.toml", "拓波_广州拓波-turbomail-系统任意用户登录.toml", "明源_明源erp-sso-login-aspx身份认证绕过.toml", "明源_明源云-erp-文档服务系统任意文件上传.toml", "易宝_易宝oa-getposition存在sql注入.toml", "汉王_汉王e脸通综合管理平台-firstpeopleopen-getdoors-do-存在sql注入.toml", "泛微_泛微-ecology9-importvalidationfieldservlet-sql-注入.toml", "泛微_泛微e-cology9-filedownloadlocation-身份认证绕过导致sql注入.toml", "泛微_泛微oa前台登录绕过.toml", "浪擎_浪擎-days-灾备-execp2vbackup-任意文件上传.toml", "深信服_深信服-dp-osm-堡垒机-rce.toml", "深信服_深信服edr-rce-cve-2025-34041.toml", "用友_用友-畅捷通-t-get-a-处存在敏感信息泄露.toml", "用友_用友-畅捷通-tplus-sql注入.toml", "绿盟_亿赛通-hookwhitelistservice-sql-注入.toml", "绿盟_亿赛通-workflowaction-sql-注入.toml", "绿盟_亿赛通电子文档安全管理系统-getmultiplekey-sql-注入.toml", "绿盟_绿盟ips-users-json信息泄露.toml", "联想_联想网盘filez-cve-2025-2068信息泄露.toml", "联想_联想网盘filez-cve-2025-2069-远程代码执行.toml", "联想_联想网盘filez-cve-2025-2070-任意文件读取.toml", "联想_联想网盘存在任意文件上传漏洞.toml", "致远_致远oa任意文件上传cve-2025-34040.toml", "若依_若依任意-件读取.toml", "蓝凌_蓝凌oa远程命令执行.toml", "装盟科技_装盟科技-家装erp管理系统wechatapi_erpmobile-ashx-sql注入.toml", "金蝶_金蝶eas-autologin-jsp远程代码执行.toml", "雄伟_雄伟科技智慧食堂系统任意用户密码重置.toml", "飞企互联_飞企互联-oa-fework-changebgservlet-命令执行.toml", "飞企互联_飞企互联-oa-fework-remoteservlet-命令执行.toml", "dataease_dataease-后台远程代码执行漏洞-cve-2025-53004.toml", "dataease_dataease-后台远程代码执行漏洞-cve-2025-53005.toml", "google_chrome-cve-2025-6554.toml", "google_谷歌浏览器chromev8存在任意命令执行漏洞.toml", "h3c_h3c-路由器前台rce.toml", "ktadmin_ktadmin-开发框架-upload文件上传漏洞.toml", "linux_sudo-chroot提权cve-2025-32463.toml", "linux_sudo提权cve-2025-32462.toml", "yak_yakit最新版本被动远程代码执行.toml", "华天动力_华天动力oa8000存在任意文件读取.toml", "华易_华易企业管理云平台-home-zy-sql-注入漏洞.toml", "和达_和达数字管理系统distributionform-sql-注入漏洞.toml", "契约锁_契约锁电子签章系统远程代码执行漏洞.toml", "开源_notepad-cve-2025-49144.toml", "开源_winrar-目录穿越漏洞-cve-2025-6218.toml", "微助教_微助教课堂管理系统indexs-文件读取漏洞.toml", "微软_exchange-存在-proxyshell绕过反序列化漏洞.toml", "汉王_汉王-e-脸通综合管理平台querymeetingfile-do-sql-注入漏洞.toml", "泛微_泛微ecology9-formmodefieldbrowserservlet接口存在sql注入.toml", "泛微_泛微ecology9filedownloadlocation任意文件下载漏洞.toml", "泛微_泛微oa后台rce.toml", "深信服_深信服运维安全管理系统存在rce.toml", "满客宝_满客宝智慧食堂管理系统存在任意文件下载.toml", "灵当_灵当-crm-getloginfo-php文件上传漏洞.toml", "用友_用友-畅捷通addresssettingcontroller存在ssrf.toml", "用友_用友-畅捷通crm-newleadset-php-存在sql注入.toml", "用友_用友-畅捷通t-fileuploadhandler任意文件上传.toml", "用友_用友-畅捷通t-getall处存在敏感信息泄露漏洞.toml", "用友_用友-畅捷通t-initcontext处存在登录绕过漏洞.toml", "用友_用友-畅捷通t-keyedit-aspx-存在sql注入.toml", "用友_用友-畅捷通t-load处存在sql注入.toml", "用友_用友-畅捷通t-save-infotofile处存在任意文件上传漏洞.toml", "红帆_红帆-ioffice-netcauserlogin-sql-注入漏洞.toml", "红海_红海ehr存在文件读取漏洞.toml", "绿盟_亿赛通hookwhitelist-sql注入.toml", "美特_美特-crm-sendfile-jsp文件上传致-rce-漏洞.toml", "雨人_雨人-erp-request-axd-信息泄露漏洞.toml", "agentsyste_agentsyste代理商管理系统-login-action-struts2-远程代码执行.toml", "ibm_ibm-websphere-application-server远程代码执行.toml", "metacrm_metacrm-客户关系管理系统-sendfile-jsp-任意文件上传.toml", "metacrm_metacrm-客户关系管理系统-sendsms-jsp-任意文件上传.toml", "信呼_信呼oa-sql注入漏洞.toml", "华测_华测监测预警系统2-2-sysgroupedit-aspx-sql注入.toml", "帆软_帆软-finereport帆软报表-print_ie_pdf-sql注入.toml", "汉王_汉王e脸通综合管理平台meetingfilemanage-do-sql注入.toml", "泛微_泛微e-cology9-sql注入.toml", "泛微_泛微e-cology9远程代码执行.toml", "泛微_泛微ecology目录遍历漏洞.toml", "浪潮_浪潮云财务系统-allotordersrv-asmx远程代码执行.toml", "浪潮_浪潮云财务系统命令执行漏洞.toml", "爱数_爱数anyshare爱数云盘start_service远程代码执行.toml", "用友_用友bip远程代码执行.toml", "用友_用友nc-changeevent-sql注入漏洞.toml", "用友_用友nc-listusersharingevents-存在sql注入.toml", "金和_金和oa-sql注入漏洞.toml", "飞致云_飞致云-dataease-postgresql-jdbc-bypass-远程代码执行漏洞-cve-2025-49001.toml", "飞致云_飞致云-dataease-postgresql-jdbc-bypass-远程代码执行漏洞-cve-2025-49002.toml", "citrix_cve-2025-5349.toml", "citrix_cve-2025-5777.toml", "citrix_cve-2025-6543.toml", "管伊佳_管伊佳erp任意文件上传.toml"]}